returned_manager/__init__.py
returned_manager/server.py
returned_manager/test.py
returned_manager/worker.py
returned_manager-0.4.dist-info/METADATA
returned_manager-0.4.dist-info/WHEEL
returned_manager-0.4.dist-info/top_level.txt
returned_manager-0.4.dist-info/RECORD
